zope/app/catalog/__init__.py
zope/app/catalog/apidoc.zcml
zope/app/catalog/attribute.py
zope/app/catalog/catalog.py
zope/app/catalog/classes.zcml
zope/app/catalog/configure.zcml
zope/app/catalog/field.py
zope/app/catalog/ftesting.zcml
zope/app/catalog/interfaces.py
zope/app/catalog/keyword.py
zope/app/catalog/subscribers.zcml
zope/app/catalog/testing.py
zope/app/catalog/tests.py
zope/app/catalog/text.py
zope/app/catalog/browser/README.rst
zope/app/catalog/browser/__init__.py
zope/app/catalog/browser/advanced.pt
zope/app/catalog/browser/catalog.py
zope/app/catalog/browser/catalog_icon.gif
zope/app/catalog/browser/configure.zcml
zope/app/catalog/browser/tests.py
zope_app_catalog-6.0.dist-info/METADATA
zope_app_catalog-6.0.dist-info/WHEEL
zope_app_catalog-6.0.dist-info/top_level.txt
zope_app_catalog-6.0.dist-info/RECORD
