Metadata-Version: 2.4
Name: zope.app.catalog
Version: 6.0
Summary: Management pages for Zope Catalog
Home-page: http://github.com/zopefoundation/zope.app.catalog
Author: Zope Foundation and Contributors
Author-email: zope-dev@zope.dev
License: ZPL-2.1
Keywords: zope3 catalog index
Classifier: Development Status :: 5 - Production/Stable
Classifier: Environment :: Web Environment
Classifier: Intended Audience :: Developers
Classifier: License :: OSI Approved :: Zope Public License
Classifier: Programming Language :: Python
Classifier: Programming Language :: Python :: 3
Classifier: Programming Language :: Python :: 3.9
Classifier: Programming Language :: Python :: 3.10
Classifier: Programming Language :: Python :: 3.11
Classifier: Programming Language :: Python :: 3.12
Classifier: Programming Language :: Python :: 3.13
Classifier: Programming Language :: Python :: Implementation :: CPython
Classifier: Natural Language :: English
Classifier: Operating System :: OS Independent
Classifier: Topic :: Internet :: WWW/HTTP
Classifier: Framework :: Zope :: 3
Requires-Python: >=3.9
Requires-Dist: setuptools
Requires-Dist: zope.catalog>=4.2.0
Provides-Extra: test
Requires-Dist: zope.app.appsetup; extra == "test"
Requires-Dist: zope.app.basicskin>=4.0.0; extra == "test"
Requires-Dist: zope.app.container>=4.0.0; extra == "test"
Requires-Dist: zope.app.component>=4.0.0; extra == "test"
Requires-Dist: zope.app.form>=5.0.0; extra == "test"
Requires-Dist: zope.app.publisher; extra == "test"
Requires-Dist: zope.app.publication; extra == "test"
Requires-Dist: zope.app.schema>=4.0.0; extra == "test"
Requires-Dist: zope.app.wsgi[testlayer]>=5.3; extra == "test"
Requires-Dist: zope.browserpage; extra == "test"
Requires-Dist: zope.browserresource; extra == "test"
Requires-Dist: zope.container; extra == "test"
Requires-Dist: zope.formlib; extra == "test"
Requires-Dist: zope.login; extra == "test"
Requires-Dist: zope.principalannotation; extra == "test"
Requires-Dist: zope.principalregistry; extra == "test"
Requires-Dist: zope.publisher; extra == "test"
Requires-Dist: zope.securitypolicy; extra == "test"
Requires-Dist: zope.testbrowser>=5.2; extra == "test"
Requires-Dist: zope.testing; extra == "test"
Requires-Dist: zope.testrunner>=6.4; extra == "test"
Requires-Dist: zope.traversing>=4.1.0; extra == "test"
Requires-Dist: webtest; extra == "test"
Dynamic: author
Dynamic: author-email
Dynamic: classifier
Dynamic: description
Dynamic: home-page
Dynamic: keywords
Dynamic: license
Dynamic: provides-extra
Dynamic: requires-dist
Dynamic: requires-python
Dynamic: summary
